my_package_hello_db/__init__.py
my_package_hello_db/main.py
my_package_hello_db-0.1.1.dist-info/METADATA
my_package_hello_db-0.1.1.dist-info/WHEEL
my_package_hello_db-0.1.1.dist-info/top_level.txt
my_package_hello_db-0.1.1.dist-info/RECORD
